pyPRMS/Exceptions_custom.py
pyPRMS/__init__.py
pyPRMS/constants.py
pyPRMS/plot_helpers.py
pyPRMS/prms_helpers.py
pyPRMS/py.typed
pyPRMS/version.py
pyPRMS/cbh/Cbh.py
pyPRMS/cbh/CbhAscii.py
pyPRMS/cbh/CbhNetcdf.py
pyPRMS/cbh/__init__.py
pyPRMS/control/Control.py
pyPRMS/control/ControlFile.py
pyPRMS/control/ControlVariable.py
pyPRMS/control/__init__.py
pyPRMS/dimensions/Dimension.py
pyPRMS/dimensions/Dimensions.py
pyPRMS/dimensions/__init__.py
pyPRMS/input/DataFile.py
pyPRMS/input/InputVariable.py
pyPRMS/input/__init__.py
pyPRMS/metadata/__init__.py
pyPRMS/metadata/metadata.py
pyPRMS/parameters/ParamDb.py
pyPRMS/parameters/Parameter.py
pyPRMS/parameters/ParameterFile.py
pyPRMS/parameters/ParameterNetCDF.py
pyPRMS/parameters/ParameterSet.py
pyPRMS/parameters/Parameters.py
pyPRMS/parameters/__init__.py
pyPRMS/summary/OutputCSV.py
pyPRMS/summary/OutputVariable.py
pyPRMS/summary/OutputVariables.py
pyPRMS/summary/__init__.py
pyPRMS/utilities/__init__.py
pyPRMS/utilities/convert_cbh.py
pyPRMS/utilities/convert_model_output.py
pyPRMS/utilities/convert_params.py
pyPRMS/xml/cbh.xml
pyPRMS/xml/control.xml
pyPRMS/xml/dimensions.xml
pyPRMS/xml/modules.xml
pyPRMS/xml/parameters.xml
pyPRMS/xml/time_series_input.xml
pyPRMS/xml/variables.xml
pyprms-0.9.7.dist-info/LICENSE.md
pyprms-0.9.7.dist-info/METADATA
pyprms-0.9.7.dist-info/WHEEL
pyprms-0.9.7.dist-info/entry_points.txt
pyprms-0.9.7.dist-info/top_level.txt
pyprms-0.9.7.dist-info/RECORD
