Metadata-Version: 2.2
Name: pyPRMS
Version: 0.9.7
Summary: Python library for Precipitation-Runoff Modeling System
Author-email: Parker Norton <pnorton@usgs.gov>
Maintainer-email: Parker Norton <pnorton@usgs.gov>
Project-URL: Repository, https://github.com/EC-USGS/pyPRMS.git
Keywords: PRMS,NHM,streamflow,hydrology,surface
Classifier: Development Status :: 3 - Alpha
Classifier: Programming Language :: Python :: 3
Requires-Python: <3.13,>=3.10
License-File: LICENSE.md
Requires-Dist: cartopy
Requires-Dist: dask
Requires-Dist: fsspec
Requires-Dist: geopandas
Requires-Dist: matplotlib
Requires-Dist: netCDF4
Requires-Dist: networkx>=2
Requires-Dist: numpy
Requires-Dist: pandas
Requires-Dist: pyproj
Requires-Dist: rich
Requires-Dist: shapely
Requires-Dist: sphinx
Requires-Dist: sphinx-autodoc-typehints
Requires-Dist: sphinx-book-theme
Requires-Dist: xarray
Provides-Extra: dev
Requires-Dist: mypy; extra == "dev"
Requires-Dist: mypy_extensions; extra == "dev"
Requires-Dist: pytest; extra == "dev"
Requires-Dist: pytest-cov; extra == "dev"
Requires-Dist: pytest-xdist; extra == "dev"
Requires-Dist: pytest-datafiles; extra == "dev"
